.gitignore
README.rst
setup.cfg
setup.py
yfind/__init__.py
yfind/find.py
yfind/parser.py
yfind.egg-info/PKG-INFO
yfind.egg-info/SOURCES.txt
yfind.egg-info/dependency_links.txt
yfind.egg-info/entry_points.txt
yfind.egg-info/not-zip-safe
yfind.egg-info/requires.txt
yfind.egg-info/top_level.txt
yfind/tests/test_parser.py