Metadata-Version: 1.1
Name: yfind
Version: 0.1.0a1
Summary: Search YAML files satisfying specified conditions.
Home-page: https://github.com/chrneumann/yfund
Author: Christian Neumann
Author-email: cneumann@datenkarussell.de
License: BSD-2-Clause
Keywords: yaml find search
Platform: UNKNOWN
Classifier: Programming Language :: Python
Classifier: Development Status :: 3 - Alpha
Classifier: Environment :: Console
Classifier: License :: OSI Approved :: BSD License
Classifier: Programming Language :: Python
Classifier: Programming Language :: Python :: 3
Classifier: Topic :: Text Processing
Classifier: Topic :: Text Processing :: Markup
